{"type":"FeatureCollection","features":[{"type":"Feature","properties":{"ville":"aflou","couleur":"rouge","superficie":8900},"geometry":{"coordinates":[0.42293191587344836,34.254316516923154],"type":"Point","test":12},"id":0},{"type":"Feature","properties":{},"geometry":{"coordinates":[5.418966412429995,32.13757784058103],"type":"Point"}},{"type":"Feature","properties":{},"geometry":{"coordinates":[7.386422531597788,36.60579070472441],"type":"Point"}},{"type":"Feature","properties":{},"geometry":{"coordinates":[4.000765394990225,36.36361490257086],"type":"Point"}},{"type":"Feature","properties":{},"geometry":{"coordinates":[-0.472048572379407,35.62893338981779],"type":"Point"}},{"type":"Feature","properties":{},"geometry":{"coordinates":[-0.9312064550202308,35.65478600629939],"type":"Point"}},{"type":"Feature","properties":{},"geometry":{"coordinates":[3.425985937362526,34.76668865526551],"type":"Point"}},{"type":"Feature","properties":{},"geometry":{"coordinates":[3.066724831013744,35.437426014726356],"type":"Point"}},{"type":"Feature","properties":{"test":"test"},"geometry":{"coordinates":[1.2519946644896152,35.41490683467828],"type":"Point"},"id":8},{"type":"Feature","properties":{},"geometry":{"coordinates":[1.3625360421962682,32.19315774775066],"type":"Point"}},{"type":"Feature","properties":{},"geometry":{"coordinates":[2.154752840811881,34.1895715191645],"type":"Point"}},{"type":"Feature","properties":{},"geometry":{"coordinates":[8.0147244608128,35.40508614444137],"type":"Point"}},{"type":"Feature","properties":{},"geometry":{"coordinates":[8.023924587193022,36.30845306286017],"type":"Point"}},{"type":"Feature","properties":{},"geometry":{"coordinates":[5.9696880047372645,36.774713903723],"type":"Point"}},{"type":"Feature","properties":{},"geometry":{"coordinates":[6.614515631516895,36.737811875174174],"type":"Point"}}]}